AUTHORS
CHANGELOG.txt
DESCRIPTION
LICENSE
MANIFEST.in
README.rst
setup.py
django_youtubeembedfield.egg-info/PKG-INFO
django_youtubeembedfield.egg-info/SOURCES.txt
django_youtubeembedfield.egg-info/dependency_links.txt
django_youtubeembedfield.egg-info/requires.txt
django_youtubeembedfield.egg-info/top_level.txt
youtubeembedfield/__init__.py
youtubeembedfield/fields.py