Metadata-Version: 1.0
Name: django-youtubeembedfield
Version: 0.1.3
Summary: A field that accepts regular YouTube links and saves the embed ones.
